remove_qcfailed_mapped/__init__.py
remove_qcfailed_mapped/main.py
remove_qcfailed_mapped-0.4.dist-info/DESCRIPTION.rst
remove_qcfailed_mapped-0.4.dist-info/METADATA
remove_qcfailed_mapped-0.4.dist-info/RECORD
remove_qcfailed_mapped-0.4.dist-info/WHEEL
remove_qcfailed_mapped-0.4.dist-info/metadata.json
remove_qcfailed_mapped-0.4.dist-info/top_level.txt
